distributed_schedule/__init__.py
distributed_schedule/client.py
distributed_schedule/config.py
distributed_schedule/handlers.py
distributed_schedule/server.py
distributed_schedule/store.py
distributed_schedule/tasks.py
distributed_schedule/times_handlers.py
local_work/__init__.py
local_work/client.py
local_work/client_api.py
local_work/server.py
local_work/task1.py
local_work/task2.py
test/__init__.py
test/test_server.py
distributed_schedule_py-0.0.2.dist-info/METADATA
distributed_schedule_py-0.0.2.dist-info/WHEEL
distributed_schedule_py-0.0.2.dist-info/entry_points.txt
distributed_schedule_py-0.0.2.dist-info/top_level.txt
distributed_schedule_py-0.0.2.dist-info/RECORD
