Metadata-Version: 2.1
Name: distributed-schedule-py
Version: 0.0.2
Summary: This is a distributed_schedule system
Home-page: UNKNOWN
Author: xiaowuzidaxia
Author-email: 609310949@qq.com
License: UNKNOWN
Platform: UNKNOWN
Classifier: Development Status :: 3 - Alpha
Classifier: Intended Audience :: Developers
Classifier: Topic :: Software Development
Classifier: License :: OSI Approved :: MIT License
Classifier: Programming Language :: Python :: 3.6
Requires-Dist: click (==7.0)
